{
  "hash": "5c65adc98d741d8b4a3f63823bcfa5ecc3df98ee",
  "title": "RED LICORICE STICKS",
  "image": "",
  "href": "https://www.finedininglovers.com/recipes/dessert/red-licorice-recipe/",
  "extension": "Chrome",
  "firstAdded": "2016-03-05T02:59:06.149000",
  "users": [
    null
  ],
  "keywords": [
    "stories",
    "blog",
    "recipes",
    "people",
    "video",
    "talk",
    "interview",
    "grant",
    "achatz",
    "elena",
    "reygadas",
    "mark",
    "olive",
    "aus",
    "pierre",
    "gagnaire",
    "yoshijiro",
    "narisawa",
    "alain",
    "ducasse",
    "best",
    "chefs",
    "world",
    "food",
    "travel",
    "paris",
    "secret",
    "bars",
    "girona",
    "krakow",
    "pln",
    "luang",
    "prabang",
    "lao",
    "vegan",
    "vancouver",
    "city",
    "tasting",
    "tours",
    "artichocke",
    "nutmeg",
    "roe",
    "caviar",
    "oysters",
    "mirtle",
    "events",
    "asias",
    "restaurants",
    "spellegrino",
    "young",
    "chef",
    "apply",
    "worlds",
    "sapori",
    "ticino",
    "bocuse",
    "dor"
  ],
  "directions": [
    "0",
    "Preparation time45 m",
    "Cooking time15 m",
    "Recipe categoryDessert",
    "Recipe yield8"
  ],
  "ingredients": [
    "0",
    "Stories",
    "Blog",
    "Recipes",
    "People",
    "Photo",
    "Video",
    "We Talk About",
    "INTERVIEW",
    "Grant Achatz, US",
    "Elena Reygadas, MX",
    "Mark Olive, AUS",
    "Pierre Gagnaire, F",
    "Yoshijiro Narisawa, JP",
    "Alain Ducasse, FR",
    "Best Chefs in the World",
    "FOOD & TRAVEL",
    "Paris, FR",
    "Secret bars in the world",
    "Girona, ES",
    "Krakow, PLN",
    "Luang Prabang, LAO",
    "Vegan Vancouver, CA",
    "City Tasting Tours",
    "FOOD A TO Z",
    "Artichocke",
    "Nutmeg",
    "Roe",
    "Caviar",
    "Oysters",
    "Mirtle",
    "EVENTS",
    "Asia's 50 Best restaurants",
    "S.Pellegrino Young Chef",
    "Apply now!",
    "World's 50 Best Restaurants",
    "S.Pellegrino Sapori Ticino",
    "Bocuse d'Or",
    "INTERVIEW",
    "Grant Achatz, US",
    "Elena Reygadas, MX",
    "Mark Olive, AUS",
    "Pierre Gagnaire, F",
    "Yoshijiro Narisawa, JP",
    "Alain Ducasse, FR",
    "Best Chefs in the World",
    "Grant Achatz, US",
    "Elena Reygadas, MX",
    "Mark Olive, AUS",
    "Pierre Gagnaire, F",
    "Yoshijiro Narisawa, JP",
    "Alain Ducasse, FR",
    "Best Chefs in the World",
    "FOOD & TRAVEL",
    "Paris, FR",
    "Secret bars in the world",
    "Girona, ES",
    "Krakow, PLN",
    "Luang Prabang, LAO",
    "Vegan Vancouver, CA",
    "City Tasting Tours",
    "Paris, FR",
    "Secret bars in the world",
    "Girona, ES",
    "Krakow, PLN",
    "Luang Prabang, LAO",
    "Vegan Vancouver, CA",
    "City Tasting Tours",
    "FOOD A TO Z",
    "Artichocke",
    "Nutmeg",
    "Roe",
    "Caviar",
    "Oysters",
    "Mirtle",
    "Artichocke",
    "Nutmeg",
    "Roe",
    "Caviar",
    "Oysters",
    "Mirtle",
    "EVENTS",
    "Asia's 50 Best restaurants",
    "S.Pellegrino Young Chef",
    "Apply now!",
    "World's 50 Best Restaurants",
    "S.Pellegrino Sapori Ticino",
    "Bocuse d'Or",
    "Asia's 50 Best restaurants",
    "S.Pellegrino Young Chef",
    "Apply now!",
    "World's 50 Best Restaurants",
    "S.Pellegrino Sapori Ticino",
    "Bocuse d'Or"
  ],
  "__v": 1
}