{
  "hash": "193352f4f4425fefa752b6d60915528b3f2adb3a",
  "title": "Soboro Beef",
  "image": "",
  "href": "http://www.bonappetit.com/recipe/soboro-beef",
  "extension": "Chrome",
  "firstAdded": "2017-01-31T14:30:15.558000",
  "users": [
    null
  ],
  "ratings": [],
  "keywords": [],
  "directions": [
    "0",
    "Heat oil in a medium skillet over medium-high. Cook beef, stirring and breaking into small pieces, until browned and nearly cooked through, about 3 minutes. Add sake and cook until evaporated, about 1 minute. Add mirin and soy sauce and cook until pan is almost dry, about 1 minute longer. Add scallions and toss to combine."
  ],
  "ingredients": [
    "0",
    "Ingredients",
    "4 SERVINGS",
    "2 teaspoons vegetable oil",
    "8 ounces ground beef chuck (20% fat)",
    "2 tablespoons sake",
    "2 tablespoons mirin (sweet Japanese rice wine)",
    "1 tablespoon soy sauce",
    "2 scallions, chopped"
  ],
  "__v": 1
}