{
  "hash": "f5c7cd34ffddc08728c1de1173ece01a51506123",
  "title": "Tarragon Salad Dressing",
  "image": "",
  "href": "http://www.food.com/recipe/tarragon-salad-dressing-67555",
  "firstAdded": "2015-01-31T19:00:49.392000",
  "users": [
    null
  ],
  "keywords": [
    "olive",
    "oil",
    "red",
    "wine",
    "cider",
    "vinegar",
    "tarragon",
    "dijon",
    "mustard",
    "clove",
    "garlic",
    "salt",
    "pepper",
    "chives",
    "parsley",
    "salad",
    "greens"
  ],
  "directions": [
    "0",
    "In a jar with a tight fitting lid, combine the first nine ingredients; shake well.",
    "Serve over salad greens."
  ],
  "ingredients": [
    "0",
    "1⁄2 cup olive oil or 1⁄2 cup vegetable oil",
    "1⁄3 cup red wine vinegar or 1⁄3 cup cider vinegar",
    "2 tablespoons minced fresh tarragon or 2 teaspoons dried tarragon",
    "1 teaspoon Dijon mustard",
    "1 clove garlic, minced",
    "1⁄2 teaspoon salt",
    "1⁄2 teaspoon pepper",
    "1⁄2 teaspoon minced chives",
    "1⁄2 teaspoon minced fresh parsley",
    "salad greens"
  ],
  "__v": 1
}