{
  "hash": "4ce0ad79203e18650be6dd9e201625a72b9bb962",
  "title": "Grandma pancakes?",
  "image": "",
  "href": "http://recipe-folder.com/recipe/5e302eaef2c88a29c17540de",
  "extension": "User Added",
  "firstAdded": "2020-01-28T12:53:02.436000",
  "users": [
    null
  ],
  "ratings": [],
  "keywords": [],
  "directions": [
    "0",
    "Mix everything except egg white.",
    "1",
    "Stiffen egg white and stir into the mixture.",
    "2",
    "Bake."
  ],
  "ingredients": [
    "0",
    "250 gr flour",
    "1",
    "1 egg",
    "2",
    "1/4 sugar",
    "3",
    "1/6 margarine stick",
    "4",
    "1 spoon baking powder",
    "5",
    "1 glass water"
  ],
  "__v": 1,
  "hidden": true
}