{
  "hash": "05d30874a0af71cbedc44c49e611abc3850585c6",
  "title": "Ramen Noodle Salad",
  "image": "https://www.chef-in-training.com/blog/wp-content/uploads/2019/05/Ramen-Noodle-Salad-1.jpg",
  "href": "http://foodizm.site/2019/05/17/ramen-noodle-salad/",
  "extension": "Chrome",
  "firstAdded": "2019-06-03T13:09:25.745000",
  "users": [
    null
  ],
  "ratings": [],
  "keywords": [],
  "directions": [
    "0",
    "In a large bowl combine all the salad ingredients and toss well.",
    "To make the dressing combine all ingredients in a small mixing bowl.",
    "Pour the dressing over the salad about 5 minutes before you are ready to serve it."
  ],
  "ingredients": [
    "0",
    "10 cups cabbage mix, About 1½ pounds",
    "½ cup shredded carrots",
    "½ cups thinly sliced green onions",
    "2 packages ramen noodles broken into small chunks, don’t use the seasoning",
    "½ cup sliced almonds",
    "¼ cups sunflower seeds"
  ],
  "__v": 1
}