{
  "__v": 1,
  "directions": [
    "0",
    "Heat olive oil in a large stockpot or Dutch oven over medium high heat. Add ground beef and onion and cook until beef has browned, about 3-5 minutes, making sure to crumble the beef as it cooks; season with salt and pepper, to taste. Drain excess fat.",
    "Stir in tomatoes, tomato sauce, chicken broth, ketchup, mustard, pasta and 2 cups water. Bring to a boil; cover, reduce heat and simmer until pasta is cooked through, about 13-16 minutes.",
    "Remove from heat and top with cheese. Cover until cheese has melted, about 2 minutes.",
    "Serve immediately, garnished with tomato and green onions, if desired."
  ],
  "firstAdded": "2014-09-17T20:12:42.508000",
  "hash": "001909590f1a11ef3858d7c5a0d542e1578b6296",
  "href": "http://damndelicious.net/2014/01/11/one-pot-cheeseburger-casserole/",
  "image": "http://damndelicious.net/wp-content/uploads/2014/01/IMG_2111edit2.jpg",
  "ingredients": [
    "0",
    "1 tablespoon olive oil",
    "1 1/2 pounds ground beef",
    "1 onion, diced",
    "Kosher salt and freshly ground black pepper, to taste",
    "1 (28-ounce) can diced tomatoes, undrained",
    "1 (8-ounce) can tomato sauce",
    "2 cups chicken broth",
    "1/4 cup ketchup",
    "2 teaspoons dijon mustard",
    "1 pound rotini pasta",
    "2 cups shredded cheddar cheese",
    "1 Roma tomato, diced",
    "2 green onions, sliced"
  ],
  "keywords": [
    "olive",
    "oil",
    "beef",
    "onion",
    "kosher",
    "salt",
    "black",
    "pepper",
    "tomatoes",
    "undrained",
    "tomato",
    "chicken",
    "broth",
    "ketchup",
    "dijon",
    "mustard",
    "rotini",
    "pasta",
    "cheddar",
    "cheese",
    "roma",
    "green",
    "onions"
  ],
  "title": "One Pot Cheeseburger Casserole",
  "users": [
    null
  ]
}