{
  "hash": "1241f8411ac58abdcbc4bad07359c458d5074a33",
  "title": "Better Than Coffee (Chicory Latte)",
  "image": "https://www.hormonesbalance.com/wp-content/uploads/2014/10/IMG_9137-1024x683.jpg",
  "href": "https://www.hormonesbalance.com/recipes/chicory-latte-almost-coffee/",
  "extension": "Chrome",
  "firstAdded": "2016-03-25T11:54:16.491000",
  "users": [
    null
  ],
  "keywords": [
    "roasted",
    "chicory",
    "root",
    "source",
    "dandelion",
    "water",
    "ghee",
    "coconut",
    "butter",
    "tolerated",
    "dates",
    "nutmeg",
    "nut"
  ],
  "directions": [
    "0",
    "Place chicory and dandelion root in a cooking pot and cover with water.",
    "Bring it to a boil, reduce the heat and simmer for 2 minutes.",
    "Turn off the heat and let it steep for 10 minutes.",
    "Strain and transfer to the blender, then add the ghee and the dates. Blend for 1 minute.",
    "Grate some fresh nutmeg and enjoy."
  ],
  "ingredients": [
    "0",
    "1 tablespoon roasted chicory root (source)",
    "1 tablespoon roasted dandelion root (source)",
    "2 cups of water",
    "2 tablespoons ghee, coconut butter or butter (if tolerated)",
    "2 pitted dates",
    "fresh nutmeg (nut or powder)"
  ],
  "__v": 1
}