{
  "hash": "0c3ee4d9c6570a24399ceb6f73b24a52d3a31ac9",
  "title": "Skinny Yogurt Marinated Chicken Kebabs",
  "image": "",
  "href": "http://www.littlebroken.com/2015/05/28/skinny-yogurt-marinated-chicken-kebabs/",
  "extension": "Chrome",
  "firstAdded": "2016-10-31T02:26:16.050000",
  "users": [
    null
  ],
  "ratings": [],
  "keywords": [],
  "directions": [
    "0",
    "In a medium bowl, combine the yogurt with garlic, chili powder, cumin, onion, olive oil, sea salt, and fresh ground black pepper, to taste. Add the chicken and stir to coat evenly. Cover and refrigerate for at least 2 hours up to overnight.",
    "When ready to cook, preheat the grill on high. Thread the pieces of chicken onto the skewers and grill, turning frequently, until chicken juices run clear, about 8-10 minutes.",
    "Sprinkle with minced parsley (optional) and serve immediately."
  ],
  "ingredients": [
    "0",
    "7 oz. plain Greek yogurt (I used Fage total)",
    "3 large garlic cloves, pressed",
    "1 tsp. chili powder",
    "1 tsp. ground cumin",
    "1 small yellow onion, grated",
    "1 Tbsp. extra-virgin olive oil",
    "½ tsp. sea salt",
    "1½ lbs. boneless, skinless, chicken thighs, cut into bite-size pieces",
    "fresh ground black pepper",
    "minced parsley, garnish (optional)"
  ],
  "__v": 1
}