{
  "hash": "63e9f47ea5bcb9ae8fc4e78c154f5b851a54989b",
  "title": "banana bread mug cake recipe",
  "image": "http://cdn.instructables.com/F03/SGF7/IGMJOZCU/F03SGF7IGMJOZCU.MEDIUM.jpg",
  "href": "http://www.instructables.com/id/banana-bread-mug-cake-recipe/",
  "extension": "Firefox",
  "firstAdded": "2015-11-10T15:35:33.054000",
  "users": [
    null
  ],
  "keywords": [
    "butter",
    "cooking",
    "oil",
    "egg",
    "milk",
    "use",
    "regular",
    "soy",
    "nut",
    "banana",
    "mashed",
    "purpose",
    "make",
    "sure",
    "scoop",
    "flour",
    "measuring",
    "brown",
    "sugar",
    "lightly",
    "baking"
  ],
  "directions": [
    "0",
    "You need a 12 oz+ mug for this! I'm using a 14 oz mug. Any smaller than 12 oz and you risk running over the edges. Plus, it's really hard to mix everything in a teeny mug.",
    "The microwave I'm using is 1000 watts.",
    "Try not to deviate from the ingredients above - I can't guarantee this will work if you substitute all the things. ;)"
  ],
  "ingredients": [
    "0",
    "1 tablespoon butter, melted OR 1 tablespoon of cooking oil",
    "1 egg, beaten",
    "1 tablespoon milk (can use regular, soy or nut)",
    "1 very ripe banana, mashed",
    "3 tablespoons of all purpose flour (make sure to scoop the flour out of the bag with a measuring spoon so you get enough!)",
    "3 tablespoons brown sugar, lightly packed",
    "1/2 teaspoon baking powder"
  ],
  "__v": 2
}