{
  "hash": "522b96255bcc4d766701fd2eb30318f45b903e68",
  "title": "Homemade Peach Pie",
  "image": "http://www.wiveswithknives.net/wp-content/uploads/2011/09/IMG_4807-1024x1022.jpg",
  "href": "http://www.wiveswithknives.net/2011/09/20/peach-pie/",
  "firstAdded": "2015-01-18T21:51:54.631000",
  "users": [
    null
  ],
  "keywords": [
    "pastry",
    "double",
    "crust",
    "pie",
    "sugar",
    "depending",
    "sweetness",
    "peaches",
    "flour",
    "cinnamon",
    "nutmeg",
    "salt",
    "vanilla",
    "butter",
    "wash",
    "egg",
    "yolk",
    "water",
    "sanding"
  ],
  "directions": [
    "0",
    "Line pie plate with pastry. Combine sugar, flour, spice and salt. Add to peaches, mix lightly. Fill shell. Dot with butter.",
    "Add top crust; crimp edges. Brush with egg wash and sprinkle with sanding sugar.",
    "Bake in a 400 degree oven for 45-50 minutes or until juices are bubbling and the crust is nicely browned.",
    "Serve warm with a big scoop of vanilla ice cream."
  ],
  "ingredients": [
    "0",
    "Pastry for a 9-10 inch double crust pie",
    "¾ - 1 cup sugar depending on sweetness of the peaches",
    "4 tablespoons flour",
    "½ teaspoon cinnamon or nutmeg",
    "dash salt",
    "1 teaspoon vanilla",
    "6 cups peeled sliced fresh peaches",
    "2 tablespoons butter",
    "egg wash made with 1 egg yolk and 2 tablespoons water",
    "sanding sugar"
  ],
  "__v": 1
}