{
  "hash": "626f8d3a5169d9fee883b46800f3c40ed17de1a6",
  "title": "Avocado Chicken Salad",
  "image": "https://data.beyonddiet.com/getimage.imhx?img=00_41_06_41_410641-165269.jpg&sw=600&sh=600&w=710&cust=2x1",
  "href": "https://www.beyonddiet.com/recipes/38345/avocado-chicken-salad?food=figs&utm_source=facebook&utm_medium=post&tag=avocadochickensalad",
  "extension": "Chrome",
  "firstAdded": "2017-01-04T18:26:19.677000",
  "users": [
    null
  ],
  "ratings": [],
  "keywords": [],
  "directions": [
    "0",
    "Directions",
    "Dice all ingredients. Combine everything in a bowl, and mix well. Eat it right out of the bowl or on top of a bed of lettuce."
  ],
  "ingredients": [
    "0",
    "Ingredients",
    "4 oz. chicken, cooked, free-range, organic",
    "2 oz. avocado, fresh, organic",
    "1/4 med. bell pepper, green, fresh, organic",
    "1/2 sml. tomatoes, red, fresh, organic",
    "1/4 sml. onion, any type, organic",
    "sea salt, unrefined, & fresh ground pepper, organic to taste"
  ],
  "__v": 1
}