{
  "hash": "30fe9b207e779c0856ee8bf6bd7367797b250132",
  "title": "Homemade Chili Seasoning",
  "image": "http://static.budgetbytes.com/wp-content/uploads/2014/01/Chili-Seasoning-1.jpg",
  "href": "http://www.budgetbytes.com/2014/01/homemade-chili-seasoning/",
  "extension": "Chrome",
  "firstAdded": "2015-03-16T23:32:00.322000",
  "users": [
    null
  ],
  "keywords": [
    "chili",
    "cumin",
    "cayenne",
    "pepper",
    "garlic",
    "onion",
    "salt"
  ],
  "directions": [
    "0",
    "Add all of the ingredients to a bowl and stir to combine. Store in an air-tight container, away from heat and moisture for up to six months."
  ],
  "ingredients": [
    "0",
    "1 Tbsp chili powder",
    "1 tsp ground cumin",
    "¼ tsp cayenne pepper",
    "¼ tsp garlic powder",
    "½ tsp onion powder",
    "1 tsp salt",
    "¼ tsp (approximately) freshly ground pepper"
  ],
  "__v": 1
}