{
  "hash": "16270c4a8d378b799f19c8a727e21ce4afaa185a",
  "title": "Scotcheroos",
  "image": "https://fbcdn-sphotos-g-a.akamaihd.net/hphotos-ak-xfa1/v/t1.0-9/10891754_899584223387271_2570584992584324751_n.jpg?oh=39638ac8658111aa561085daea716431&oe=5535AB99&__gda__=1429111983_e61b71e6e3cefdf8ec48b3a38a881f32",
  "href": "https://www.facebook.com/photo.php?fbid=899449203400773&set=a.104367579575610.8957.100000071048190&type=1&theater",
  "firstAdded": "2014-12-27T17:49:57.007000",
  "users": [
    null
  ],
  "keywords": [
    "sugar",
    "white",
    "corn",
    "syrup",
    "creamy",
    "peanut",
    "butter",
    "rice",
    "krispies",
    "semisweet",
    "chocolate",
    "chips",
    "milk",
    "butterscotch"
  ],
  "directions": [
    "0",
    "Directions:",
    "1 In a heavy sauce pan cook sugar, syrup and butter over a medium heat until sugar is dissolved.",
    "2 Remove from heat and add peanut butter. In a large bowl mix into the rice krispies until krispies are coated and press firmly into a buttered 9 x 12 inch pan.",
    "3 In a double boiler melt butterscotch and chocolate chips until soft and creamy. Then pour and spread over the uncut bars in the pan.",
    "4 When they are cool cut into the size bars you like to serve.",
    "5 I warn you -- these will make you yearn for more until every last one is gone! . And consider yourselves lucky cuz it took me nine years to get her recipe! No other Scotcheroos are as good as hers!",
    "6"
  ],
  "ingredients": [
    "0",
    "Ingredients",
    "1 cup sugar",
    "1 cup white corn syrup",
    "1 cup creamy peanut butter",
    "6 cups Rice Krispies",
    "2 tablespoons butter",
    "1/2 cup semi-sweet chocolate chips",
    "1 1/2 cups milk chocolate chips",
    "1 cup butterscotch chips"
  ],
  "__v": 1
}