{
  "hash": "c44a089631752fcfb586a861ca3b15f74c35472c",
  "title": "Banana Bread",
  "image": "http://www.alexandracooks.com/wp-content/uploads/2012/07/bananabread4_a.jpg",
  "href": "http://www.alexandracooks.com/2012/03/08/mrs-myers-banana-bread/",
  "extension": "Chrome",
  "firstAdded": "2015-06-09T22:44:42.059000",
  "users": [
    null
  ],
  "keywords": [
    "sugar",
    "butter",
    "softened",
    "sifted",
    "flour",
    "sift",
    "baking",
    "soda",
    "salt",
    "eggs",
    "use",
    "vanilla",
    "nuts",
    "buttermilk",
    "mashed",
    "bananas",
    "overripe"
  ],
  "directions": [
    "0",
    "Preheat the oven to 350ºF. Butter two loaf pans. (I butter generously.)",
    "In a stand mixer, cream butter and sugar until light and fluffy.",
    "Meanwhile, in a separate bowl, whisk together flour, baking soda and salt.",
    "With the mixer on low, add the eggs one at a time, beating after each addition. Add the vanilla, buttermilk and bananas.",
    "Add the flour mixture and mix until just combined. Divide batter between the two prepared pans. Bake for approximately 1 hour.",
    "Remove from oven and turn loaves out onto cooling rack immediately. Let cool."
  ],
  "ingredients": [
    "0",
    "2 cups sugar",
    "1 cup butter, softened",
    "3 cups sifted flour (I never sift)",
    "1 tsp. baking soda",
    "1 tsp. table salt",
    "5 eggs (I use 4)",
    "2 tsp. vanilla extract",
    "1 cup nuts (I never add nuts)",
    "1/2 cup buttermilk",
    "1 quart mashed bananas*, about 8 (ripe to overripe)"
  ],
  "__v": 1
}