{
  "hash": "df9ebea8b61f9e4bb178b905520ca583b83ae165",
  "title": "CHEESE ENCHILADAS",
  "image": "http://www.caciqueinc.com/wp-content/uploads/2016/05/CheeseEnchilada-1.jpg",
  "href": "http://www.caciqueinc.com/recipes/cheese-enchiladas/",
  "extension": "Chrome",
  "firstAdded": "2017-04-15T20:40:46.132000",
  "users": [
    null
  ],
  "ratings": [],
  "keywords": [],
  "directions": [
    "0",
    "HOW TO MAKE IT",
    "Preheat oven to 350°F.",
    "In a mixing bowl, combine Manchego and Queso Fresco. Bring the enchilada sauce to a boil in a medium saucepan over lower heat. Dip each tortilla, one at a time, in sauce until soft (about 10 seconds) and carefully place each tortilla onto a baking sheet. Spoon cheese mixture onto the tortilla, reserving ½ cup for garnish . Roll and arrange enchilada seam down in pan. Repeat with each tortilla.",
    "Cover enchiladas with remaining sauce and bake for 15 - 20 minutes. Top with Crema Mexicana and cheese mixture. Serve hot."
  ],
  "ingredients": [
    "0",
    "®",
    "®"
  ],
  "__v": 1
}