{
  "hash": "2dc0a4eac29883372e976c6460b89d2a8db3f810",
  "title": "Broccoli Salad",
  "image": "https://i2.wp.com/www.thestatenislandfamily.com/wp-content/uploads/2018/01/Broccoli-Salad.png?resize=150%2C150&ssl=1",
  "href": "https://www.thestatenislandfamily.com/easiest-broccoli-salad/",
  "extension": "Chrome",
  "firstAdded": "2020-02-11T13:53:32.378000",
  "users": [
    null
  ],
  "ratings": [],
  "keywords": [],
  "directions": [
    "0",
    "Combine all of the ingredients for the broccoli salad in a mixing bowl and set aside.",
    "In a separate bowl combine the ingredients for the dressing.",
    "Thoroughly mix the dressing and the salad together to coat evenly. If you choose to use cheese, sprinkle it on top."
  ],
  "ingredients": [
    "0",
    "3 cups washed and chopped broccoli",
    "1 cup finely chopped purple cabbage",
    "½ cup shredded carrot",
    "¼ cup dried cranberries",
    "¼ cup shredded cheddar optional",
    "1 tablespoon fat free mayonnaise",
    "1 teaspoon lemon juice"
  ],
  "__v": 1
}