{
  "hash": "7d44a4daff3fb45a21799c217ca739fbca47705f",
  "title": "Disneyland's Hot Chocolate",
  "image": "https://www.onionringsandthings.com/wp-content/uploads/2016/11/disneylands-hot-chocolate-copycat-1-1.jpg",
  "href": "https://www.onionringsandthings.com/disneylands-hot-chocolate-copycat/",
  "extension": "Chrome",
  "firstAdded": "2018-10-22T16:45:23.472000",
  "users": [
    null
  ],
  "ratings": [],
  "keywords": [],
  "directions": [
    "0",
    "In a saucepan, combine milk and heavy cream. Over medium heat, bring to a simmer. Do not bring to a boil!",
    "In a small bowl, combine cocoa powder, grated chocolate, and about 1/2 cup of the heated milk. Stir until smooth. Slowly add to saucepan, whisking vigorously until completely combined.",
    "Add condensed milk and vanilla extract. Stir until well combined. Simmer for about 3 to 5 minutes.",
    "To serve, ladle into serving cups. Top with whipped cream and lightly dust with ground cinnamon or cocoa powder, if desired."
  ],
  "ingredients": [
    "0",
    "3 cups milk",
    "1 cup heavy cream",
    "1/2 cup cocoa powder",
    "1/2 cup milk chocolate, grated",
    "14 ounces condensed milk",
    "1/8 teaspoon vanilla extract",
    "whipped cream",
    "ground cinnamon"
  ],
  "__v": 1
}