{
  "hash": "7eeca363818a0133b527aca4eaa4d41f29aeb83d",
  "title": "Свекла, томленная с маслом",
  "image": "http://recipe-folder.com/img/recipe-images/023/035/2845012823.jpg",
  "href": "https://www.facebook.com/carrotodessa/photos/pcb.1647462862160000/1647462652160021/?type=3&theater",
  "extension": "Chrome",
  "firstAdded": "2016-01-11T13:41:05.498000",
  "users": [
    null
  ],
  "keywords": [],
  "directions": [
    "0",
    "Свеклу натереть оливковым маслом, завернуть в фольгу и запекать до мягкости , около часа.",
    "Дать немного остыть. Потом очистить и нарезать поперек или ломтиками. Растопить грамм 50 сливочного масла, добавить оливкового и потомить на минимальном огне около 10 минут.",
    "Уже на столе присыпать перцем, солью и рубленой петрушкой. Сбрызнуть бальзамическим уксусом."
  ],
  "ingredients": [
    "0",
    "50 сливочного масла",
    "Свекла",
    "перец, соль",
    "петрушка"
  ],
  "__v": 2
}