{
  "hash": "d86fce9303f6f072c86e89bc85c20983e34ee3d1",
  "title": "Fresh Strawberry Cobbler",
  "image": "http://divascancook.com/wp-content/uploads/2013/06/Screen-Shot-2013-06-19-at-1.17.20-PM.png",
  "href": "http://divascancook.com/fresh-strawberry-cobbler-recipe-easy-dessert/",
  "firstAdded": "2014-12-11T19:29:11.902000",
  "users": [
    null
  ],
  "keywords": [
    "strawberries",
    "sugar",
    "allpurpose",
    "flour",
    "baking",
    "salt",
    "milk",
    "vanilla",
    "butter"
  ],
  "directions": [
    "0",
    "Preheat oven to 375.",
    "In a medium bowl, add strawberries and ¾ cup sugar.",
    "Stir to coat strawberries in sugar and set aside.",
    "In a large bowl whisk together flour, baking powder, salt and sugar.",
    "Add in milk, vanilla extract and melted butter.",
    "Stir until combined. A few lumps are ok.",
    "Grease a 9-inch casserole dish.",
    "Pour batter evenly into dish.",
    "Spoon strawberries evenly on top of batter. Do NOT stir.",
    "Baked for 35-40 minutes or until golden.",
    "Serve warm or cold."
  ],
  "ingredients": [
    "0",
    "3 cups fresh strawberries, diced",
    "½-3/4 cup sugar",
    "1 cup all-purpose flour",
    "2 teaspoons baking powder",
    "½ teaspoon salt",
    "½ cup sugar",
    "1 cup milk",
    "½ teaspoon vanilla extract",
    "1 stick butter, melted"
  ],
  "__v": 1
}