{
  "hash": "5b3f3b06dccbb065c5a23ac35577765910c23f98",
  "title": "Oatmeal Energy balls",
  "image": "",
  "href": "https://recipe4diaries.com/oatmeal-energy-balls/",
  "extension": "Chrome",
  "firstAdded": "2018-08-29T20:08:42.758000",
  "users": [
    null
  ],
  "ratings": [],
  "keywords": [],
  "directions": [
    "0",
    "Preparation :",
    "Mix oats, peanut butter, raisins, and honey together with a fork in a bowl. Knead mixture by hand until fully incorporated; roll into 1-inch balls. Refrigerate for at least 1 hour."
  ],
  "ingredients": [
    "0",
    "Ingredients",
    "1 1/2 cups rolled oats",
    "3/4 cup natural peanut butter",
    "1/2 cup raisins",
    "2 tablespoons honey"
  ],
  "__v": 1
}