{
  "hash": "0fdc7212aca456223112dcb9a7d3aa51534bf56e",
  "title": "Hasselback Potatoes",
  "image": "http://4.bp.blogspot.com/_wjO9ZSr8ZTA/Sgue8xHj5AI/AAAAAAAAFcw/aGwiCDkVZ50/s800/IMG_0030.JPG",
  "href": "http://www.seasaltwithfood.com/2009/05/hasselback-potatoes.html",
  "extension": "Chrome",
  "firstAdded": "2015-12-27T21:57:43.371000",
  "users": [
    null
  ],
  "keywords": [
    "medium",
    "size",
    "potatoes",
    "garlic",
    "olive",
    "oil",
    "butter",
    "maldon",
    "salt",
    "black",
    "pepper"
  ],
  "directions": [
    "0",
    "Preheat the oven to 220˚C (425˚F). Put the potato on a chopping board, flat side down. Start from one end of the potato, cut almost all the way through, at about 3 to 4 mm intervals.",
    "Arrange the potatoes in a baking tray and insert the garlic in between the slits. Scatter some butter on top of each potato. Then drizzle the olive oil and sprinkle some sea salt and freshly ground black pepper.",
    "Bake the potatoes for about 40 minutes or until the potatoes turn crispy and the flesh is soft."
  ],
  "ingredients": [
    "0",
    "6 Medium Size Potatoes",
    "2 - 3 Cloves Garlic, thinly sliced",
    "2 Tbsp Olive Oil",
    "30 g Butter",
    "Maldon Sea Salt",
    "Freshly Ground Black Pepper"
  ],
  "__v": 1
}