{
  "hash": "a07f7eb9a5217dd0034177ab3ebd77b605f7e8e1",
  "title": "Crunchy Cabbage Salad with Miso-Ginger Dressing",
  "image": "https://images.food52.com/Iz5WG66VHSyuoTAvmwZeUIEgIko=/753x502/03cd6a03-56d0-4574-b35a-9249eb8881b2--food52-01-22-13-6450.jpg",
  "href": "https://food52.com/recipes/20537-crunchy-cabbage-salad-with-miso-ginger-dressing",
  "extension": "",
  "firstAdded": "2018-01-28T23:29:56.766000",
  "users": [
    null
  ],
  "ratings": [],
  "keywords": [],
  "directions": [
    "0",
    "In a small bowl, whisk together the ginger, garlic, miso, vinegar, soy sauce, sesame oil and water. and set it aside.",
    "In a large bowl, toss the cabbage, carrots and sesame seeds together with the dressing. Serve immediately if you like it very crunchy or let it sit covered in the refrigerator for up to a few hours if you prefer it more slaw-like."
  ],
  "ingredients": [
    "0",
    "1 teaspoon finely grated fresh ginger",
    "1 small garlic clove, grated",
    "2 tablespoons miso paste",
    "2 tablespoons rice wine vinegar",
    "1 tablespoon soy sauce",
    "1 teaspoon toasted sesame oil",
    "2 tablespoons water",
    "3 cups finely shredded cabbage (about ¾ pound cabbage)",
    "1 large carrot, peeled and cut into very thin matchsticks",
    "1 tablespoon black sesame seeds, toasted"
  ],
  "__v": 1
}