{
  "__v": 2,
  "directions": [
    "0",
    "Preheat oven to 350 degrees F. Roll dough out on lightly floured surface to thickness of 1/8 inch. Fit into 10-inch pie pan or quiche dish. Trim and finish edges. Using electric mixer, cream butter and sugar. Beat in eggs 1 at a time. Blend in half and half and vanilla. Stir in chocolate chips and pecans. Pour into crust. Bake 30 minutes. Reduce oven temperature to 300 degrees F and continue baking until pie is set, about 50 minutes. Cool; pie will fall. (Can be prepared 1 day ahead. Cover and refrigerate.)",
    "Spoon whipped cream into a pastry bag fitted with star tip. Pipe rosettes of whipped cream around edge of pie. Garnish with chocolate shavings."
  ],
  "firstAdded": "2014-11-17T16:57:33.281000",
  "hash": "800fd3b0425f71b5ca25465dc0f50ce265b80a67",
  "href": "http://www.pepperplate.com/recipes/view.aspx?id=3410597",
  "image": "",
  "ingredients": [
    "0",
    "Pie Crust",
    "1/2 cup (1 stick) butter, room temperature",
    "3 cups firmly packed golden brown sugar",
    "3 eggs, room temperature",
    "1/2 cup half and half",
    "1 teaspoon vanilla extract",
    "1 6-ounce package semisweet chocolate chips",
    "1/2 cup chopped pecans",
    "1/2 cup whipping cream, whipped",
    "Chocolate shavings"
  ],
  "keywords": [
    "pie",
    "crust",
    "butter",
    "room",
    "firmly",
    "golden",
    "brown",
    "sugar",
    "eggs",
    "vanilla",
    "semisweet",
    "chocolate",
    "chips",
    "pecans",
    "whipping",
    "cream",
    "whipped",
    "shavings"
  ],
  "title": "Chocolate Chip Butterscotch Pie",
  "users": [
    null
  ]
}